pygiftbit/__init__.py
pygiftbit/__main__.py
pygiftbit/errors.py
pygiftbit/giftbit.py
pygiftbit-1.0.3.dist-info/LICENSE
pygiftbit-1.0.3.dist-info/METADATA
pygiftbit-1.0.3.dist-info/WHEEL
pygiftbit-1.0.3.dist-info/top_level.txt
pygiftbit-1.0.3.dist-info/RECORD
