Metadata-Version: 2.1
Name: pygiftbit
Version: 1.0.3
Summary: A simple Python wrapper for the Giftbit API
Home-page: https://github.com/da-code-a/pygiftbit
Author: Dakota Brown
Author-email: dakota.kae.brown@gmail.com
License: MIT
Platform: UNKNOWN
Classifier: License :: OSI Approved :: MIT License
Classifier: Programming Language :: Python :: 3
Classifier: Programming Language :: Python :: 3.6
Requires-Dist: requests
